Metadata-Version: 2.1
Name: clanimate
Version: 0.0.1
Summary: A CLI loading bar and animation python library.
Home-page: https://github.com/jwlodek/clanimate
Author: Jakub Wlodek
Author-email: jwlodek.dev@gmail.com
License: BSD (3-clause)
Keywords: animation cli commandline progressbar
Platform: UNKNOWN
Classifier: Development Status :: 3 - Alpha
Classifier: Intended Audience :: Developers
Classifier: Programming Language :: Python :: 3.2
Classifier: Programming Language :: Python :: 3.3
Classifier: Programming Language :: Python :: 3.4
Classifier: Programming Language :: Python :: 3.5
Classifier: Programming Language :: Python :: 3.6
Classifier: Programming Language :: Python :: 3.7
Requires-Python: >=3.2
